gtimelog/CONTRIBUTORS.rst
gtimelog/__init__.py
gtimelog/about.ui
gtimelog/debian-paths.py
gtimelog/gtimelog-large.png
gtimelog/gtimelog.css
gtimelog/gtimelog.png
gtimelog/gtimelog.ui
gtimelog/main.py
gtimelog/menus.ui
gtimelog/paths.py
gtimelog/preferences.ui
gtimelog/secrets.py
gtimelog/settings.py
gtimelog/shortcuts.ui
gtimelog/timelog.py
gtimelog/utils.py
gtimelog/data/gschemas.compiled
gtimelog/data/org.gtimelog.gschema.xml
gtimelog/locale/en/LC_MESSAGES/gtimelog.mo
gtimelog/locale/fr/LC_MESSAGES/gtimelog.mo
gtimelog/locale/lt/LC_MESSAGES/gtimelog.mo
gtimelog/locale/nb/LC_MESSAGES/gtimelog.mo
gtimelog/locale/nl/LC_MESSAGES/gtimelog.mo
gtimelog/po/POTFILES.in
gtimelog/po/en.po
gtimelog/po/fr.po
gtimelog/po/gtimelog.pot
gtimelog/po/lt.po
gtimelog/po/nb.po
gtimelog/po/nl.po
gtimelog/tests/__init__.py
gtimelog/tests/__main__.py
gtimelog/tests/test_main.py
gtimelog/tests/test_settings.py
gtimelog/tests/test_timelog.py
gtimelog-0.12.0.dist-info/COPYING
gtimelog-0.12.0.dist-info/METADATA
gtimelog-0.12.0.dist-info/WHEEL
gtimelog-0.12.0.dist-info/entry_points.txt
gtimelog-0.12.0.dist-info/top_level.txt
gtimelog-0.12.0.dist-info/RECORD
