Metadata-Version: 2.1
Name: gtimelog
Version: 0.12.0
Summary: A Gtk+ time tracking application
Home-page: https://gtimelog.org/
Author: Marius Gedminas
Author-email: marius@gedmin.as
License: GPL
Keywords: time log logging timesheets gnome gtk
Classifier: Development Status :: 4 - Beta
Classifier: Environment :: X11 Applications :: GTK
Classifier: License :: OSI Approved :: GNU General Public License (GPL)
Classifier: Programming Language :: Python :: 3.7
Classifier: Programming Language :: Python :: 3.8
Classifier: Programming Language :: Python :: 3.9
Classifier: Programming Language :: Python :: 3.10
Classifier: Programming Language :: Python :: 3.11
Classifier: Programming Language :: Python :: 3.12
Classifier: Programming Language :: Python :: Implementation :: CPython
Classifier: Programming Language :: Python :: Implementation :: PyPy
Classifier: Topic :: Office/Business
Requires-Python: >= 3.7
License-File: COPYING
Requires-Dist: PyGObject
Provides-Extra: test
Requires-Dist: freezegun ; extra == 'test'
